README.md
setup.cfg
setup.py
time_series_transform/__init__.py
time_series_transform.egg-info/PKG-INFO
time_series_transform.egg-info/SOURCES.txt
time_series_transform.egg-info/dependency_links.txt
time_series_transform.egg-info/requires.txt
time_series_transform.egg-info/top_level.txt
time_series_transform/io/__init__.py
time_series_transform/io/arrow.py
time_series_transform/io/base.py
time_series_transform/io/feather.py
time_series_transform/io/generator.py
time_series_transform/io/numpy.py
time_series_transform/io/pandas.py
time_series_transform/io/parquet.py
time_series_transform/plot/__init__.py
time_series_transform/plot/base.py
time_series_transform/plot/stock_plot.py
time_series_transform/plot/time_series_plot.py
time_series_transform/stock_transform/__init__.py
time_series_transform/stock_transform/base.py
time_series_transform/stock_transform/stock_extractor.py
time_series_transform/stock_transform/stock_transfromer.py
time_series_transform/stock_transform/util.py
time_series_transform/stock_transform/stock_engine/__init__.py
time_series_transform/stock_transform/stock_engine/_investing.py
time_series_transform/stock_transform/stock_engine/_yahoo_stock.py
time_series_transform/stock_transform/stock_engine/engine_interface.py
time_series_transform/test/__init__.py
time_series_transform/test/test_io.py
time_series_transform/test/test_sklearn.py
time_series_transform/test/test_stock_base.py
time_series_transform/test/test_stock_extract.py
time_series_transform/test/test_stock_transform.py
time_series_transform/test/test_tfDataset_adopter.py
time_series_transform/test/test_time_series_base.py
time_series_transform/test/test_time_series_transform.py
time_series_transform/transform_core_api/__init__.py
time_series_transform/transform_core_api/base.py
time_series_transform/transform_core_api/tfDataset_adopter.py
time_series_transform/transform_core_api/time_series_transformer.py
time_series_transform/transform_core_api/util.py