Metadata-Version: 2.1
Name: time-series-transform
Version: 1.1.2
Summary: A data preprocessing package for time series data. It provides tools for machine learing and deep learning.It also has subsection specialized in stock.
Home-page: https://github.com/allen-chiang/Time-Series-Transformer
Author: Kuan-Lun Chiang; Kuan-Yu Chiang
Author-email: kuanlun.chiang@outlook.com
License: MIT
Download-URL: https://github.com/allen-chiang/Time-Series-Transformer/archive/1.1.2.tar.gz
Project-URL: Source Code, https://github.com/allen-chiang/Time-Series-Transformer
Project-URL: Documentation, https://allen-chiang.github.io/Time-Series-Transformer/
Keywords: time series,stock,machine learning,deep learning
Platform: UNKNOWN
Classifier: Intended Audience :: Science/Research
Classifier: Intended Audience :: Developers
Classifier: Programming Language :: Python
Classifier: Topic :: Software Development
Classifier: Topic :: Scientific/Engineering
Classifier: License :: OSI Approved :: MIT License
Classifier: Programming Language :: Python :: 3
Classifier: Programming Language :: Python :: 3.6
Classifier: Programming Language :: Python :: 3.7
Classifier: Programming Language :: Python :: 3.8
